{
  "name": "backend",
  "version": "1.0.0",
  "description": "",
  "main": "index.js",
  "scripts": {
    "test": "echo \"Error: no test specified\" && exit 1",
    "start": "nodemon -x node src/server.js",
    "debug": "nodemon -x node --inspect src/server.js"
  },
  "keywords": [],
  "author": "Rachna Bansal <rachnasinghal2005@gmail.com> (https://github.com/rachnaban)",
  "license": "MIT",
  "dependencies": {
    "babel-preset-env": "1.7.0",
    "bcryptjs": "2.4.3",
    "cookie-parser": "1.4.3",
    "dotenv": "6.1.0",
    "jsonwebtoken": "8.4.0",
    "nodemon": "1.18.6",
    "npm-run-all": "4.1.3"
  },
  "babel": {
    "presets": [
      "env"
    ]
  }
}
